huawei_b593_status/__init__.py
huawei_b593_status-0.0.2.dist-info/DESCRIPTION.rst
huawei_b593_status-0.0.2.dist-info/METADATA
huawei_b593_status-0.0.2.dist-info/RECORD
huawei_b593_status-0.0.2.dist-info/WHEEL
huawei_b593_status-0.0.2.dist-info/metadata.json
huawei_b593_status-0.0.2.dist-info/top_level.txt
