Metadata-Version: 2.0
Name: huawei-b593-status
Version: 0.0.2
Summary: Huawei B593 status fetcher
Home-page: https://github.com/ojarva/python-huawei-b593-status
Author: Olli Jarva
Author-email: olli@jarva.fi
License: BSD
Keywords: huawei 4g b593
Platform: UNKNOWN
Classifier: Development Status :: 4 - Beta
Classifier: Intended Audience :: Developers
Classifier: Intended Audience :: System Administrators
Classifier: License :: OSI Approved :: BSD License
Classifier: Programming Language :: Python :: 2.6
Classifier: Programming Language :: Python :: 2.7
Classifier: Programming Language :: Python :: 3
Classifier: Programming Language :: Python :: 3.2
Classifier: Programming Language :: Python :: 3.3
Classifier: Programming Language :: Python :: 3.4
Classifier: Programming Language :: Python :: Implementation :: PyPy
Requires-Dist: httplib2 (>=0.9.2)
Requires-Dist: xmltodict (>=0.10.1)
Provides-Extra: dev
Requires-Dist: twine; extra == 'dev'
Requires-Dist: wheel; extra == 'dev'
